zigpy_cc/__init__.py
zigpy_cc/api.py
zigpy_cc/buffalo.py
zigpy_cc/config.py
zigpy_cc/const.py
zigpy_cc/definition.py
zigpy_cc/exception.py
zigpy_cc/types.py
zigpy_cc/uart.py
zigpy_cc/zpi_object.py
zigpy_cc/zigbee/__init__.py
zigpy_cc/zigbee/application.py
zigpy_cc/zigbee/backup.py
zigpy_cc/zigbee/common.py
zigpy_cc/zigbee/nv_items.py
zigpy_cc/zigbee/start_znp.py
zigpy_cc-0.5.2.dist-info/COPYING
zigpy_cc-0.5.2.dist-info/LICENSE
zigpy_cc-0.5.2.dist-info/METADATA
zigpy_cc-0.5.2.dist-info/WHEEL
zigpy_cc-0.5.2.dist-info/top_level.txt
zigpy_cc-0.5.2.dist-info/RECORD
