Metadata-Version: 2.1
Name: zigpy-cc
Version: 0.5.2
Summary: A library which communicates with Texas Instruments CC2531 radios for zigpy
Home-page: http://github.com/zigpy/zigpy-cc
Author: Balazs Sandor
Author-email: sanyatuning@gmail.com
License: GPL-3.0
Platform: UNKNOWN
Requires-Dist: pyserial-asyncio
Requires-Dist: zigpy (>=0.23.1)
